{
    "version": {
        "id": 1296054,
        "crate": "zksync_protobuf_build",
        "num": "0.5.0",
        "dl_path": "/api/v1/crates/zksync_protobuf_build/0.5.0/download",
        "readme_path": "/api/v1/crates/zksync_protobuf_build/0.5.0/readme",
        "updated_at": "2024-10-09T16:25:27.134221Z",
        "created_at": "2024-10-09T16:25:27.134221Z",
        "downloads": 66562,
        "features": {},
        "yanked": false,
        "yank_message": null,
        "lib_links": null,
        "license": "MIT OR Apache-2.0",
        "links": {
            "dependencies": "/api/v1/crates/zksync_protobuf_build/0.5.0/dependencies",
            "version_downloads": "/api/v1/crates/zksync_protobuf_build/0.5.0/downloads",
            "authors": "/api/v1/crates/zksync_protobuf_build/0.5.0/authors"
        },
        "crate_size": 11165,
        "published_by": {
            "id": 278214,
            "login": "ml-ia",
            "name": null,
            "avatar": "https://avatars.githubusercontent.com/u/152983389?v=4",
            "url": "https://github.com/ml-ia"
        },
        "audit_actions": [
            {
                "action": "publish",
                "user": {
                    "id": 278214,
                    "login": "ml-ia",
                    "name": null,
                    "avatar": "https://avatars.githubusercontent.com/u/152983389?v=4",
                    "url": "https://github.com/ml-ia"
                },
                "time": "2024-10-09T16:25:27.134221Z"
            }
        ],
        "checksum": "4121952bcaf711005dd554612fc6e2de9b30cb58088508df87f1d38046ce8ac8",
        "rust_version": null,
        "has_lib": true,
        "bin_names": [],
        "edition": "2021",
        "description": "ZKsync consensus protobuf codegen",
        "homepage": "https://matter-labs.io/",
        "documentation": null,
        "repository": "https://github.com/matter-labs/era-consensus",
        "trustpub_data": null,
        "linecounts": {
            "languages": {
                "Rust": {
                    "code_lines": 717,
                    "comment_lines": 31,
                    "files": 4
                }
            },
            "total_code_lines": 717,
            "total_comment_lines": 31
        }
    }
}